Workbook

Sheet Diccionario
A1: Diccionario de codificación — RAFFÜSS para Durey
A3: Estructura del código (SKU): CATEGORÍA - TIPO - CALIDAD - TALLA - COLOR
A4: Ejemplo: NIN-TOB-AFE-T03-NEG = Niño · tobillera · afelpada · talla 3 · negro
A5: Código de barras = SKU + “-12D” (1 etiqueta = 12 docenas = 144 pares)
A6: Las celdas amarillas y los códigos marcados (confirmar) deben validarse con el cliente.
A8: Categoría | B8: Significado | D8: Tipo (silueta) | E8: Significado
A9: BEB | B9: Bebés | D9: TOB | E9: Tobillera
A10: NIN | B10: Niños | D10: MCA | E10: Media caña
A11: DAM | B11: Damas | D11: LAR | E11: Larga / bota
A12: CAB | B12: Caballeros / adultos | D12: INV | E12: Invisible
A13: FUT | B13: Fútbol / deportivo
A16: Calidad | B16: Significado | D16: Talla | E16: Significado
A17: AFE | B17: Afelpada (gruesa) | D17: T02 | E17: Talla 2 (niño)
A18: DEL | B18: Delgada (fina) | D18: T03 | E18: Talla 3 (niño)
D19: T04 | E19: Talla 4 (niño)
A20: Color | B20: Significado | D20: T05 | E20: Talla 5 (niño)
A21: NEG | B21: Negro | D21: TUN | E21: Talla única (confirmar adulto/dama)
A22: BLA | B22: Blanco
A23: AZU | B23: Azul
A24: MAR | B24: Marino
A25: GRI | B25: Gris | D25: Paquete | E25: Significado
A26: ROJ | B26: Rojo | D26: 12D | E26: Paquete de 12 docenas = 144 pares
A27: VER | B27: Verde
A28: (+) | B28: Agregar según paleta

Sheet Mano de obra
A1: Mano de obra — costo por docena
A2: 11 mesas · pago por hora. Ajuste las celdas amarillas con datos reales.
A4: Sueldo por hora (S/) | B4: 6
A5: Horas por día | B5: 8
A6: Docenas por persona / día (108–150) | B6: 120
A7: Sueldo por día (S/) | B7: =B4*B5 -> 48
A8: Costo M.O. por docena (S/) | B8: =B7/B6 -> 0.4
A9: Costo M.O. por paquete 12 doc (S/) | B9: =B8*12 -> 4.8
A11: Capacidad equipo en acabado = 11 mesas × docenas/persona/día
A12: Capacidad acabado (docenas/día) | B12: =11*B6 -> 1320

Sheet Maestro de modelos
A1: Maestro de modelos — código y costeo
A2: Azul = dato a ingresar · Negro = fórmula · Verde = enlace a Mano de obra. Las filas son ejemplos: reemplace con sus modelos.
A4: Categoría | B4: Tipo | C4: Calidad | D4: Talla | E4: Color | F4: Código SKU | G4: Peso x docena (g) | H4: Costo hilo (S//g) | I4: Material / doc (S/) | J4: M.O. / doc (S/) | K4: Costo total / doc (S/) | L4: Precio mayorista / doc (S/) | M4: Margen | N4: Código de barras (12 doc)
A5: NIN | B5: TOB | C5: AFE | D5: T03 | E5: NEG | F5: =A5&"-"&B5&"-"&C5&"-"&D5&"-"&E5 -> NIN-TOB-AFE-T03-NEG | G5: 360 | H5: 0.03 | I5: =G5*H5 -> 10.8 | J5: ='Mano de obra'!$B$8 -> 0.4 | K5: =I5+J5 -> 11.2 | L5: 18 | M5: =IFERROR((L5-K5)/L5,"") -> 0.37777778 | N5: =F5&"-12D" -> NIN-TOB-AFE-T03-NEG-12D
A6: NIN | B6: TOB | C6: DEL | D6: T03 | E6: BLA | F6: =A6&"-"&B6&"-"&C6&"-"&D6&"-"&E6 -> NIN-TOB-DEL-T03-BLA | G6: 240 | H6: 0.03 | I6: =G6*H6 -> 7.2 | J6: ='Mano de obra'!$B$8 -> 0.4 | K6: =I6+J6 -> 7.6 | L6: 14 | M6: =IFERROR((L6-K6)/L6,"") -> 0.45714286 | N6: =F6&"-12D" -> NIN-TOB-DEL-T03-BLA-12D
A7: NIN | B7: MCA | C7: AFE | D7: T04 | E7: AZU | F7: =A7&"-"&B7&"-"&C7&"-"&D7&"-"&E7 -> NIN-MCA-AFE-T04-AZU | G7: 420 | H7: 0.03 | I7: =G7*H7 -> 12.6 | J7: ='Mano de obra'!$B$8 -> 0.4 | K7: =I7+J7 -> 13 | L7: 20 | M7: =IFERROR((L7-K7)/L7,"") -> 0.35 | N7: =F7&"-12D" -> NIN-MCA-AFE-T04-AZU-12D
A8: CAB | B8: MCA | C8: DEL | D8: TUN | E8: NEG | F8: =A8&"-"&B8&"-"&C8&"-"&D8&"-"&E8 -> CAB-MCA-DEL-TUN-NEG | G8: 300 | H8: 0.032 | I8: =G8*H8 -> 9.6 | J8: ='Mano de obra'!$B$8 -> 0.4 | K8: =I8+J8 -> 10 | L8: 22 | M8: =IFERROR((L8-K8)/L8,"") -> 0.54545455 | N8: =F8&"-12D" -> CAB-MCA-DEL-TUN-NEG-12D
A9: FUT | B9: LAR | C9: AFE | D9: TUN | E9: VER | F9: =A9&"-"&B9&"-"&C9&"-"&D9&"-"&E9 -> FUT-LAR-AFE-TUN-VER | G9: 600 | H9: 0.032 | I9: =G9*H9 -> 19.2 | J9: ='Mano de obra'!$B$8 -> 0.4 | K9: =I9+J9 -> 19.6 | L9: 30 | M9: =IFERROR((L9-K9)/L9,"") -> 0.34666667 | N9: =F9&"-12D" -> FUT-LAR-AFE-TUN-VER-12D
A10: DAM | B10: TOB | C10: DEL | D10: TUN | E10: GRI | F10: =A10&"-"&B10&"-"&C10&"-"&D10&"-"&E10 -> DAM-TOB-DEL-TUN-GRI | G10: 200 | H10: 0.03 | I10: =G10*H10 -> 6 | J10: ='Mano de obra'!$B$8 -> 0.4 | K10: =I10+J10 -> 6.4 | L10: 13 | M10: =IFERROR((L10-K10)/L10,"") -> 0.50769231 | N10: =F10&"-12D" -> DAM-TOB-DEL-TUN-GRI-12D
